pypi_practice/_init_.py
pypi_practice_ds7-0.0.1.dist-info/METADATA
pypi_practice_ds7-0.0.1.dist-info/WHEEL
pypi_practice_ds7-0.0.1.dist-info/top_level.txt
pypi_practice_ds7-0.0.1.dist-info/RECORD
