Metadata-Version: 2.4
Name: pypi-practice-ds7
Version: 0.0.1
Summary: Practice package for PyPI
Author-email: DS7 <example@example.com>
License: MIT
Requires-Python: >=3.8
